<?xml version="1.0" encoding="UTF-8" standalone="yes"?><ns2:GridDefinitionFileOutputV2 xmlns:ns2="http://www.gtech.com/xml/eInstants/base/common/CatAdminV1"><GridBody><GridProperties><Version>18</Version><GameType>0</GameType><GridSize>5000000</GridSize><RevFileSig>Ksg6K2izDBZkqBOBE8IoDxZsVL72ki+nQKmrmr6djSULfM1mseBC8lQza62xG6cFk9ja1yDn/Gvu9+CtAntevA==</RevFileSig><BigEndianFlg>false</BigEndianFlg><SiteID>56</SiteID><PricePoint>50</PricePoint><BetUnits>1</BetUnits><ValidationUnits>1</ValidationUnits><NoOfDivisions>31</NoOfDivisions><LongName>Tiki Tac Totems</LongName><ShortName>TT009</ShortName><GridMethod>1</GridMethod><GridTrigger>1</GridTrigger><GridTriggerUnit>0</GridTriggerUnit><VendorID>1</VendorID><IntAuditVendorID>2</IntAuditVendorID><ExtAuditVendorID>0</ExtAuditVendorID><DeliveryChannel>3</DeliveryChannel><Jackpot>false</Jackpot></GridProperties><DivisionRow><Winners>4</Winners><WinAmt>150000</WinAmt><PrizeTableAmt>50000</PrizeTableAmt><PrizeType>0</PrizeType></DivisionRow><DivisionRow><Winners>10</Winners><WinAmt>100000</WinAmt><PrizeTableAmt>5000</PrizeTableAmt><PrizeType>0</PrizeType></DivisionRow><DivisionRow><Winners>10</Winners><WinAmt>50000</WinAmt><PrizeTableAmt>1000</PrizeTableAmt><PrizeType>0</PrizeType></DivisionRow><DivisionRow><Winners>15</Winners><WinAmt>15000</WinAmt><PrizeTableAmt>500</PrizeTableAmt><PrizeType>0</PrizeType></DivisionRow><DivisionRow><Winners>15</Winners><WinAmt>10150</WinAmt><PrizeTableAmt>150</PrizeTableAmt><PrizeType>0</PrizeType></DivisionRow><DivisionRow><Winners>20</Winners><WinAmt>10050</WinAmt><PrizeTableAmt>50</PrizeTableAmt><PrizeType>0</PrizeType></DivisionRow><DivisionRow><Winners>30</Winners><WinAmt>10000</WinAmt><PrizeTableAmt>0</PrizeTableAmt><PrizeType>0</PrizeType></DivisionRow><DivisionRow><Winners>50</Winners><WinAmt>5000</WinAmt><PrizeTableAmt>0</PrizeTableAmt><PrizeType>0</PrizeType></DivisionRow><DivisionRow><Winners>75</Winners><WinAmt>3000</WinAmt><PrizeTableAmt>0</PrizeTableAmt><PrizeType>0</PrizeType></DivisionRow><DivisionRow><Winners>100</Winners><WinAmt>2500</WinAmt><PrizeTableAmt>0</PrizeTableAmt><PrizeType>0</PrizeType></DivisionRow><DivisionRow><Winners>150</Winners><WinAmt>2000</WinAmt><PrizeTableAmt>0</PrizeTableAmt><PrizeType>0</PrizeType></DivisionRow><DivisionRow><Winners>250</Winners><WinAmt>1500</WinAmt><PrizeTableAmt>0</PrizeTableAmt><PrizeType>0</PrizeType></DivisionRow><DivisionRow><Winners>350</Winners><WinAmt>1300</WinAmt><PrizeTableAmt>0</PrizeTableAmt><PrizeType>0</PrizeType></DivisionRow><DivisionRow><Winners>450</Winners><WinAmt>1200</WinAmt><PrizeTableAmt>0</PrizeTableAmt><PrizeType>0</PrizeType></DivisionRow><DivisionRow><Winners>650</Winners><WinAmt>1100</WinAmt><PrizeTableAmt>0</PrizeTableAmt><PrizeType>0</PrizeType></DivisionRow><DivisionRow><Winners>900</Winners><WinAmt>1000</WinAmt><PrizeTableAmt>0</PrizeTableAmt><PrizeType>0</PrizeType></DivisionRow><DivisionRow><Winners>1250</Winners><WinAmt>800</WinAmt><PrizeTableAmt>0</PrizeTableAmt><PrizeType>0</PrizeType></DivisionRow><DivisionRow><Winners>1750</Winners><WinAmt>700</WinAmt><PrizeTableAmt>0</PrizeTableAmt><PrizeType>0</PrizeType></DivisionRow><DivisionRow><Winners>2500</Winners><WinAmt>650</WinAmt><PrizeTableAmt>0</PrizeTableAmt><PrizeType>0</PrizeType></DivisionRow><DivisionRow><Winners>3650</Winners><WinAmt>600</WinAmt><PrizeTableAmt>0</PrizeTableAmt><PrizeType>0</PrizeType></DivisionRow><DivisionRow><Winners>4400</Winners><WinAmt>550</WinAmt><PrizeTableAmt>0</PrizeTableAmt><PrizeType>0</PrizeType></DivisionRow><DivisionRow><Winners>5000</Winners><WinAmt>500</WinAmt><PrizeTableAmt>0</PrizeTableAmt><PrizeType>0</PrizeType></DivisionRow><DivisionRow><Winners>8500</Winners><WinAmt>450</WinAmt><PrizeTableAmt>0</PrizeTableAmt><PrizeType>0</PrizeType></DivisionRow><DivisionRow><Winners>12000</Winners><WinAmt>350</WinAmt><PrizeTableAmt>0</PrizeTableAmt><PrizeType>0</PrizeType></DivisionRow><DivisionRow><Winners>19500</Winners><WinAmt>300</WinAmt><PrizeTableAmt>0</PrizeTableAmt><PrizeType>0</PrizeType></DivisionRow><DivisionRow><Winners>48000</Winners><WinAmt>250</WinAmt><PrizeTableAmt>0</PrizeTableAmt><PrizeType>0</PrizeType></DivisionRow><DivisionRow><Winners>80000</Winners><WinAmt>200</WinAmt><PrizeTableAmt>0</PrizeTableAmt><PrizeType>0</PrizeType></DivisionRow><DivisionRow><Winners>155000</Winners><WinAmt>150</WinAmt><PrizeTableAmt>0</PrizeTableAmt><PrizeType>0</PrizeType></DivisionRow><DivisionRow><Winners>504593</Winners><WinAmt>100</WinAmt><PrizeTableAmt>0</PrizeTableAmt><PrizeType>0</PrizeType></DivisionRow><DivisionRow><Winners>579349</Winners><WinAmt>50</WinAmt><PrizeTableAmt>0</PrizeTableAmt><PrizeType>0</PrizeType></DivisionRow><DivisionRow><Winners>3571429</Winners><WinAmt>0</WinAmt><PrizeTableAmt>0</PrizeTableAmt><PrizeType>0</PrizeType></DivisionRow><GridRefill><SalesThreshold>3000</SalesThreshold></GridRefill></GridBody><GridFooter><checksum enc="hex">E156735F10D70921771874C3D6C217B576C87FEEF09A5D12690D411B2DFAE71B</checksum></GridFooter></ns2:GridDefinitionFileOutputV2>